IODA/IODA_model.pt
IODA/anonymize_video.py
IODA/args.py
IODA/dali_pipeline.py
IODA/format_net_output.py
IODA/initialize.py
IODA/loss.py
IODA/lstm_alexnet.py
IODA/resume.py
IODA/train.py
IODA/utils.py
IODA/validate.py
ioda-1.0.0.dist-info/METADATA
ioda-1.0.0.dist-info/WHEEL
ioda-1.0.0.dist-info/RECORD
