Metadata-Version: 2.1
Name: IODA
Version: 1.0.0
Summary: Inside Outside Discrimination Algorithm (IODA)
Home-page: https://gitlab.com/aicor/ioda
License: MIT
Author: André Schulze
Author-email: andre.schulze@med.uni-heidelberg.de
Requires-Python: >=3.9,<3.12
Classifier: License :: OSI Approved :: MIT License
Classifier: Programming Language :: Python :: 3
Classifier: Programming Language :: Python :: 3.9
Classifier: Programming Language :: Python :: 3.10
Classifier: Programming Language :: Python :: 3.11
Requires-Dist: numpy (>=1.26.2,<2.0.0)
Requires-Dist: nvidia-dali-cuda110 (>=1.32.0,<2.0.0)
Requires-Dist: scikit-learn (>=1.3.2,<2.0.0)
Requires-Dist: tensorboard (>=2.15.1,<3.0.0)
Requires-Dist: torch (>=1.13.1,<2.0.0)
Requires-Dist: torchvision (>=0.14.1,<0.15.0)
Requires-Dist: tqdm (>=4.64.1,<5.0.0)
Project-URL: Repository, https://gitlab.com/aicor/ioda
